ament_cmake_gtest/_dummy.cpython-313-x86_64-linux-gnu.so
ros_ament_cmake_gtest-2.7.3.data/data/share/ament_cmake_gtest/local_setup.bash
ros_ament_cmake_gtest-2.7.3.data/data/share/ament_cmake_gtest/local_setup.dsv
ros_ament_cmake_gtest-2.7.3.data/data/share/ament_cmake_gtest/local_setup.sh
ros_ament_cmake_gtest-2.7.3.data/data/share/ament_cmake_gtest/local_setup.zsh
ros_ament_cmake_gtest-2.7.3.data/data/share/ament_cmake_gtest/package.dsv
ros_ament_cmake_gtest-2.7.3.data/data/share/ament_cmake_gtest/package.xml
ros_ament_cmake_gtest-2.7.3.data/data/share/ament_cmake_gtest/cmake/ament_add_gtest.cmake
ros_ament_cmake_gtest-2.7.3.data/data/share/ament_cmake_gtest/cmake/ament_add_gtest_executable.cmake
ros_ament_cmake_gtest-2.7.3.data/data/share/ament_cmake_gtest/cmake/ament_add_gtest_test.cmake
ros_ament_cmake_gtest-2.7.3.data/data/share/ament_cmake_gtest/cmake/ament_cmake_gtest-extras.cmake
ros_ament_cmake_gtest-2.7.3.data/data/share/ament_cmake_gtest/cmake/ament_cmake_gtestConfig-version.cmake
ros_ament_cmake_gtest-2.7.3.data/data/share/ament_cmake_gtest/cmake/ament_cmake_gtestConfig.cmake
ros_ament_cmake_gtest-2.7.3.data/data/share/ament_cmake_gtest/cmake/ament_find_gtest.cmake
ros_ament_cmake_gtest-2.7.3.data/data/share/ament_cmake_gtest/environment/ament_prefix_path.dsv
ros_ament_cmake_gtest-2.7.3.data/data/share/ament_cmake_gtest/environment/ament_prefix_path.sh
ros_ament_cmake_gtest-2.7.3.data/data/share/ament_cmake_gtest/environment/path.dsv
ros_ament_cmake_gtest-2.7.3.data/data/share/ament_cmake_gtest/environment/path.sh
ros_ament_cmake_gtest-2.7.3.data/data/share/ament_index/resource_index/package_run_dependencies/ament_cmake_gtest
ros_ament_cmake_gtest-2.7.3.data/data/share/ament_index/resource_index/packages/ament_cmake_gtest
ros_ament_cmake_gtest-2.7.3.data/data/share/ament_index/resource_index/parent_prefix_path/ament_cmake_gtest
ros_ament_cmake_gtest-2.7.3.dist-info/METADATA
ros_ament_cmake_gtest-2.7.3.dist-info/WHEEL
ros_ament_cmake_gtest-2.7.3.dist-info/top_level.txt
ros_ament_cmake_gtest-2.7.3.dist-info/RECORD
