Metadata-Version: 2.4
Name: ros-ament-cmake-gtest
Version: 2.7.3
Summary: Wheel for the ament_cmake_gtest (ros-ament-cmake-gtest) ROS 2 package.
Dynamic: description
Dynamic: description-content-type
Dynamic: summary
